setup.cfg
setup.py
k5viz/__init__.py
k5viz.egg-info/PKG-INFO
k5viz.egg-info/SOURCES.txt
k5viz.egg-info/dependency_links.txt
k5viz.egg-info/entry_points.txt
k5viz.egg-info/requires.txt
k5viz.egg-info/top_level.txt