Metadata-Version: 1.1
Name: k5viz
Version: 1.0
Summary: k5viz is a simple application that can read in a k5 file or JSON graph file and visualize the Deep Learning neural network for you
Home-page: https://github.com/sio2boss/k5viz
Author: sio2boss
Author-email: sio2boss@hotmail.com
License: UNKNOWN
Download-URL: https://github.com/sio2boss/k5viz/tarball/1.0
Keywords: k5,visualization,visualize,deep learning,neural network
Platform: UNKNOWN
